conduits/__init__.py
conduits/pipeline.py
conduits-0.2.1.dist-info/METADATA
conduits-0.2.1.dist-info/WHEEL
conduits-0.2.1.dist-info/top_level.txt
conduits-0.2.1.dist-info/RECORD
