Metadata-Version: 2.1
Name: conduits
Version: 0.2.1
Summary: UNKNOWN
Home-page: https://github.com/kmiller96/conduits
Author: Kale Miller
License: UNKNOWN
Platform: UNKNOWN
Requires-Python: >=3.6
Requires-Dist: pandas
Requires-Dist: networkx[default]
Requires-Dist: joblib
